{"heading":90,"x":38,"y":65,"size":0.25,"rotationStyle":"normal","physicsMode":"no","costumeIndex":0,"visible":true,"isDraggable":false,"collisionPivot":{"x":0,"y":0},"collisionShapeType":"none","collisionShapeParams":[],"costumes":[{"x":100,"y":100,"faceRight":0,"bitmapResolution":1,"name":"默认","path":"默认.svg","builder_id":"tqJVWrWyGvOcQRPzA2_HE"},{"x":100,"y":100,"faceRight":0,"bitmapResolution":1,"name":"__animation_animation_默认","path":"__animation_animation_默认.svg","builder_id":"_IK4ve3R0yyeXjp285JIc"},{"x":100,"y":100,"faceRight":0,"bitmapResolution":1,"name":"__animation_animation2_默认","path":"__animation_animation2_默认.svg","builder_id":"OjnMyQyuBMR21P1_rD2qf"}],"fAnimations":{"animation":{"frameFrom":"__animation_animation_默认","frameTo":"__animation_animation_默认","frameFps":1,"onStart":{"play":"水滴声"},"builder_id":"uh6iJNcS4Py6gqKaeXj26"},"animation2":{"frameFrom":"__animation_animation2_默认","frameTo":"__animation_animation2_默认","frameFps":10,"builder_id":"dGDWN5EnMZsf_PCq0fuEK"}},"animBindings":{},"builder_id":"wTFhhWsl11odlSsiU0Fqh","builder_assetMetadata":{"id":"480","createdAt":"2025-05-07T02:04:56.275Z","updatedAt":"2025-05-08T12:26:31.081Z","owner":"curator","displayName":"魔法药水1","type":"sprite","category":"Fantasy","filesHash":"h1:wOwQgawbuhslOSxeWADWE8Kw76Y=","visibility":"public"}}