{"heading":90,"x":0,"y":0,"size":1,"rotationStyle":"normal","physicsMode":"no","costumeIndex":0,"visible":true,"isDraggable":false,"collisionPivot":{"x":0,"y":0},"collisionShapeType":"none","collisionShapeParams":[],"costumes":[{"x":100,"y":100,"faceRight":0,"bitmapResolution":2,"name":"bwalk01","path":"bwalk01.png","builder_id":"SZzAdcpnhtHuLi3vxu3Qf"}],"fAnimations":{},"animBindings":{},"builder_id":"7KsGj4nGTAELLpJcr99rS","builder_assetMetadata":{"id":"699","createdAt":"2025-10-26T07:12:55.266Z","updatedAt":"2025-10-26T07:12:55.266Z","owner":"wx_user_HhX0NYqI","displayName":"BadB08","type":"sprite","category":"*","filesHash":"h1:BH+cE2iZFilkx9N/6Y55YFEG28A=","visibility":"private"}}